{
  "version": "7",
  "dialect": "postgresql",
  "entries": [
    {
      "idx": 0,
      "version": "7",
      "when": 1782130827883,
      "tag": "0000_sweet_tag",
      "breakpoints": true
    },
    {
      "idx": 1,
      "version": "7",
      "when": 1782910733437,
      "tag": "0001_ancient_butterfly",
      "breakpoints": true
    },
    {
      "idx": 2,
      "version": "7",
      "when": 1783062656595,
      "tag": "0002_redundant_thunderbolts",
      "breakpoints": true
    },
    {
      "idx": 3,
      "version": "7",
      "when": 1783069498598,
      "tag": "0003_cuddly_the_watchers",
      "breakpoints": true
    },
    {
      "idx": 4,
      "version": "7",
      "when": 1783083629602,
      "tag": "0004_silent_patriot",
      "breakpoints": true
    },
    {
      "idx": 5,
      "version": "7",
      "when": 1783673375448,
      "tag": "0005_tidy_wilson_fisk",
      "breakpoints": true
    },
    {
      "idx": 6,
      "version": "7",
      "when": 1783686716148,
      "tag": "0006_first_ronan",
      "breakpoints": true
    },
    {
      "idx": 7,
      "version": "7",
      "when": 1783924008036,
      "tag": "0007_white_sprite",
      "breakpoints": true
    }
  ]
}